{
    "variable": [
        {
            "id": "baseUrl",
            "key": "baseUrl",
            "type": "string",
            "name": "string",
            "value": "http:\/\/localhost"
        }
    ],
    "info": {
        "name": "Livepost",
        "_postman_id": "1a8a6e93-cf0f-4c6c-8ffe-77bee8f35e9a",
        "description": "",
        "schema": "https:\/\/schema.getpostman.com\/json\/collection\/v2.1.0\/collection.json"
    },
    "item": [
        {
            "name": "Comment Management",
            "description": "\nAPIs to manage the comment resource",
            "item": [
                {
                    "name": "Display a listing of the comments.",
                    "request": {
                        "url": {
                            "host": "{{baseUrl}}",
                            "path": "api\/v1\/comments",
                            "query": [
                                {
                                    "key": "page_size",
                                    "value": "12",
                                    "description": "Size per page. Defaults to 20.",
                                    "disabled": false
                                },
                                {
                                    "key": "page",
                                    "value": "7",
                                    "description": "Page to view.",
                                    "disabled": false
                                }
                            ],
                            "raw": "{{baseUrl}}\/api\/v1\/comments?page_size=12&page=7"
                        },
                        "method": "GET",
                        "header": [
                            {
                                "key": "Content-Type",
                                "value": "application\/json"
                            },
                            {
                                "key": "Accept",
                                "value": "application\/json"
                            }
                        ],
                        "body": null,
                        "description": "Gets a list of users",
                        "auth": {
                            "type": "noauth"
                        }
                    },
                    "response": [
                        {
                            "header": [
                                {
                                    "key": "cache-control",
                                    "value": "no-cache, private"
                                },
                                {
                                    "key": "content-type",
                                    "value": "application\/json"
                                },
                                {
                                    "key": "x-ratelimit-limit",
                                    "value": "60"
                                },
                                {
                                    "key": "x-ratelimit-remaining",
                                    "value": "55"
                                },
                                {
                                    "key": "access-control-allow-origin",
                                    "value": "*"
                                }
                            ],
                            "code": 200,
                            "body": "{\"data\":[],\"links\":{\"first\":\"http:\\\/\\\/localhost\\\/api\\\/v1\\\/comments?page=1\",\"last\":\"http:\\\/\\\/localhost\\\/api\\\/v1\\\/comments?page=1\",\"prev\":\"http:\\\/\\\/localhost\\\/api\\\/v1\\\/comments?page=6\",\"next\":null},\"meta\":{\"current_page\":7,\"from\":null,\"last_page\":1,\"links\":[{\"url\":\"http:\\\/\\\/localhost\\\/api\\\/v1\\\/comments?page=6\",\"label\":\"&laquo; Previous\",\"active\":false},{\"url\":\"http:\\\/\\\/localhost\\\/api\\\/v1\\\/comments?page=1\",\"label\":\"1\",\"active\":false},{\"url\":null,\"label\":\"Next &raquo;\",\"active\":false}],\"path\":\"http:\\\/\\\/localhost\\\/api\\\/v1\\\/comments\",\"per_page\":12,\"to\":null,\"total\":3}}",
                            "name": ""
                        }
                    ]
                },
                {
                    "name": "Display the specified resource.",
                    "request": {
                        "url": {
                            "host": "{{baseUrl}}",
                            "path": "api\/v1\/comments\/:id",
                            "query": [],
                            "raw": "{{baseUrl}}\/api\/v1\/comments\/:id",
                            "variable": [
                                {
                                    "id": "id",
                                    "key": "id",
                                    "value": "1",
                                    "description": "The ID of the comment."
                                }
                            ]
                        },
                        "method": "GET",
                        "header": [
                            {
                                "key": "Content-Type",
                                "value": "application\/json"
                            },
                            {
                                "key": "Accept",
                                "value": "application\/json"
                            }
                        ],
                        "body": null,
                        "description": "",
                        "auth": {
                            "type": "noauth"
                        }
                    },
                    "response": [
                        {
                            "header": [
                                {
                                    "key": "cache-control",
                                    "value": "no-cache, private"
                                },
                                {
                                    "key": "content-type",
                                    "value": "application\/json"
                                },
                                {
                                    "key": "x-ratelimit-limit",
                                    "value": "60"
                                },
                                {
                                    "key": "x-ratelimit-remaining",
                                    "value": "54"
                                },
                                {
                                    "key": "access-control-allow-origin",
                                    "value": "*"
                                }
                            ],
                            "code": 200,
                            "body": "{\"data\":{\"id\":1,\"body\":[],\"user_id\":7,\"post_id\":2,\"created_at\":\"2024-01-06 16:29:38\",\"updated_at\":\"2024-01-06 16:29:38\"}}",
                            "name": ""
                        }
                    ]
                },
                {
                    "name": "Store a newly created resource in storage.",
                    "request": {
                        "url": {
                            "host": "{{baseUrl}}",
                            "path": "api\/v1\/comments",
                            "query": [],
                            "raw": "{{baseUrl}}\/api\/v1\/comments"
                        },
                        "method": "POST",
                        "header": [
                            {
                                "key": "Content-Type",
                                "value": "application\/json"
                            },
                            {
                                "key": "Accept",
                                "value": "application\/json"
                            }
                        ],
                        "body": null,
                        "description": "",
                        "auth": {
                            "type": "noauth"
                        }
                    },
                    "response": []
                },
                {
                    "name": "Update the specified resource in storage.",
                    "request": {
                        "url": {
                            "host": "{{baseUrl}}",
                            "path": "api\/v1\/comments\/:id",
                            "query": [],
                            "raw": "{{baseUrl}}\/api\/v1\/comments\/:id",
                            "variable": [
                                {
                                    "id": "id",
                                    "key": "id",
                                    "value": "1",
                                    "description": "The ID of the comment."
                                }
                            ]
                        },
                        "method": "PATCH",
                        "header": [
                            {
                                "key": "Content-Type",
                                "value": "application\/json"
                            },
                            {
                                "key": "Accept",
                                "value": "application\/json"
                            }
                        ],
                        "body": null,
                        "description": "",
                        "auth": {
                            "type": "noauth"
                        }
                    },
                    "response": []
                },
                {
                    "name": "Remove the specified resource from storage.",
                    "request": {
                        "url": {
                            "host": "{{baseUrl}}",
                            "path": "api\/v1\/comments\/:id",
                            "query": [],
                            "raw": "{{baseUrl}}\/api\/v1\/comments\/:id",
                            "variable": [
                                {
                                    "id": "id",
                                    "key": "id",
                                    "value": "1",
                                    "description": "The ID of the comment."
                                }
                            ]
                        },
                        "method": "DELETE",
                        "header": [
                            {
                                "key": "Content-Type",
                                "value": "application\/json"
                            },
                            {
                                "key": "Accept",
                                "value": "application\/json"
                            }
                        ],
                        "body": null,
                        "description": "",
                        "auth": {
                            "type": "noauth"
                        }
                    },
                    "response": []
                }
            ]
        },
        {
            "name": "Post Management",
            "description": "\nAPIs to manage the post resource",
            "item": [
                {
                    "name": "Display a listing of the resource.",
                    "request": {
                        "url": {
                            "host": "{{baseUrl}}",
                            "path": "api\/v1\/posts",
                            "query": [],
                            "raw": "{{baseUrl}}\/api\/v1\/posts"
                        },
                        "method": "GET",
                        "header": [
                            {
                                "key": "Content-Type",
                                "value": "application\/json"
                            },
                            {
                                "key": "Accept",
                                "value": "application\/json"
                            }
                        ],
                        "body": null,
                        "description": "",
                        "auth": {
                            "type": "noauth"
                        }
                    },
                    "response": [
                        {
                            "header": [
                                {
                                    "key": "cache-control",
                                    "value": "no-cache, private"
                                },
                                {
                                    "key": "content-type",
                                    "value": "application\/json"
                                },
                                {
                                    "key": "x-ratelimit-limit",
                                    "value": "60"
                                },
                                {
                                    "key": "x-ratelimit-remaining",
                                    "value": "53"
                                },
                                {
                                    "key": "access-control-allow-origin",
                                    "value": "*"
                                }
                            ],
                            "code": 200,
                            "body": "{\"data\":[{\"id\":1,\"title\":\"untitled\",\"body\":[]},{\"id\":2,\"title\":\"untitled\",\"body\":[]},{\"id\":3,\"title\":\"untitled\",\"body\":[]},{\"id\":5,\"title\":\"title 2\",\"body\":\"Body 2\"},{\"id\":6,\"title\":\"title 2\",\"body\":\"Body 2\"},{\"id\":7,\"title\":\"title 2\",\"body\":\"Body 2\"},{\"id\":8,\"title\":\"test title 2\",\"body\":\"Test body 2\"},{\"id\":11,\"title\":\"test title 3 updated\",\"body\":\"Test body 3 updated\"},{\"id\":12,\"title\":\"test post creation\",\"body\":[]},{\"id\":13,\"title\":\"test post creation\",\"body\":[]},{\"id\":14,\"title\":\"Test post creation\",\"body\":[]},{\"id\":15,\"title\":\"Test post creation\",\"body\":[]},{\"id\":16,\"title\":\"est\",\"body\":[]},{\"id\":17,\"title\":\"Test post creation\",\"body\":[]},{\"id\":18,\"title\":\"placeat\",\"body\":[]},{\"id\":19,\"title\":\"Test post creation\",\"body\":[]},{\"id\":20,\"title\":\"quos\",\"body\":[]},{\"id\":21,\"title\":\"Test post creation\",\"body\":[]},{\"id\":22,\"title\":\"quibusdam\",\"body\":[]},{\"id\":23,\"title\":\"Test post creation\",\"body\":[]}],\"links\":{\"first\":\"http:\\\/\\\/localhost\\\/api\\\/v1\\\/posts?page=1\",\"last\":\"http:\\\/\\\/localhost\\\/api\\\/v1\\\/posts?page=2\",\"prev\":null,\"next\":\"http:\\\/\\\/localhost\\\/api\\\/v1\\\/posts?page=2\"},\"meta\":{\"current_page\":1,\"from\":1,\"last_page\":2,\"links\":[{\"url\":null,\"label\":\"&laquo; Previous\",\"active\":false},{\"url\":\"http:\\\/\\\/localhost\\\/api\\\/v1\\\/posts?page=1\",\"label\":\"1\",\"active\":true},{\"url\":\"http:\\\/\\\/localhost\\\/api\\\/v1\\\/posts?page=2\",\"label\":\"2\",\"active\":false},{\"url\":\"http:\\\/\\\/localhost\\\/api\\\/v1\\\/posts?page=2\",\"label\":\"Next &raquo;\",\"active\":false}],\"path\":\"http:\\\/\\\/localhost\\\/api\\\/v1\\\/posts\",\"per_page\":20,\"to\":20,\"total\":36}}",
                            "name": ""
                        }
                    ]
                },
                {
                    "name": "Display the specified resource.",
                    "request": {
                        "url": {
                            "host": "{{baseUrl}}",
                            "path": "api\/v1\/posts\/:id",
                            "query": [],
                            "raw": "{{baseUrl}}\/api\/v1\/posts\/:id",
                            "variable": [
                                {
                                    "id": "id",
                                    "key": "id",
                                    "value": "1",
                                    "description": "The ID of the post."
                                }
                            ]
                        },
                        "method": "GET",
                        "header": [
                            {
                                "key": "Content-Type",
                                "value": "application\/json"
                            },
                            {
                                "key": "Accept",
                                "value": "application\/json"
                            }
                        ],
                        "body": null,
                        "description": "",
                        "auth": {
                            "type": "noauth"
                        }
                    },
                    "response": [
                        {
                            "header": [
                                {
                                    "key": "cache-control",
                                    "value": "no-cache, private"
                                },
                                {
                                    "key": "content-type",
                                    "value": "application\/json"
                                },
                                {
                                    "key": "x-ratelimit-limit",
                                    "value": "60"
                                },
                                {
                                    "key": "x-ratelimit-remaining",
                                    "value": "52"
                                },
                                {
                                    "key": "access-control-allow-origin",
                                    "value": "*"
                                }
                            ],
                            "code": 200,
                            "body": "{\"data\":{\"id\":1,\"title\":\"untitled\",\"body\":[]}}",
                            "name": ""
                        }
                    ]
                },
                {
                    "name": "Store a newly created resource in storage.",
                    "request": {
                        "url": {
                            "host": "{{baseUrl}}",
                            "path": "api\/v1\/posts",
                            "query": [],
                            "raw": "{{baseUrl}}\/api\/v1\/posts"
                        },
                        "method": "POST",
                        "header": [
                            {
                                "key": "Content-Type",
                                "value": "application\/json"
                            },
                            {
                                "key": "Accept",
                                "value": "application\/json"
                            }
                        ],
                        "body": {
                            "mode": "raw",
                            "raw": "{\"title\":\"eos\",\"body\":\"molestiae\",\"user_ids\":[]}"
                        },
                        "description": "",
                        "auth": {
                            "type": "noauth"
                        }
                    },
                    "response": []
                },
                {
                    "name": "Update the specified resource in storage.",
                    "request": {
                        "url": {
                            "host": "{{baseUrl}}",
                            "path": "api\/v1\/posts\/:id",
                            "query": [],
                            "raw": "{{baseUrl}}\/api\/v1\/posts\/:id",
                            "variable": [
                                {
                                    "id": "id",
                                    "key": "id",
                                    "value": "1",
                                    "description": "The ID of the post."
                                }
                            ]
                        },
                        "method": "PATCH",
                        "header": [
                            {
                                "key": "Content-Type",
                                "value": "application\/json"
                            },
                            {
                                "key": "Accept",
                                "value": "application\/json"
                            }
                        ],
                        "body": null,
                        "description": "",
                        "auth": {
                            "type": "noauth"
                        }
                    },
                    "response": []
                },
                {
                    "name": "Remove the specified resource from storage.",
                    "request": {
                        "url": {
                            "host": "{{baseUrl}}",
                            "path": "api\/v1\/posts\/:id",
                            "query": [],
                            "raw": "{{baseUrl}}\/api\/v1\/posts\/:id",
                            "variable": [
                                {
                                    "id": "id",
                                    "key": "id",
                                    "value": "1",
                                    "description": "The ID of the post."
                                }
                            ]
                        },
                        "method": "DELETE",
                        "header": [
                            {
                                "key": "Content-Type",
                                "value": "application\/json"
                            },
                            {
                                "key": "Accept",
                                "value": "application\/json"
                            }
                        ],
                        "body": null,
                        "description": "",
                        "auth": {
                            "type": "noauth"
                        }
                    },
                    "response": []
                }
            ]
        },
        {
            "name": "User Management",
            "description": "\nAPIs to manage the user resource",
            "item": [
                {
                    "name": "Display a listing of the users.",
                    "request": {
                        "url": {
                            "host": "{{baseUrl}}",
                            "path": "api\/v1\/users",
                            "query": [
                                {
                                    "key": "page_size",
                                    "value": "5",
                                    "description": "Size per page. Defaults to",
                                    "disabled": false
                                },
                                {
                                    "key": "page",
                                    "value": "1",
                                    "description": "Page to view.",
                                    "disabled": false
                                }
                            ],
                            "raw": "{{baseUrl}}\/api\/v1\/users?page_size=5&page=1"
                        },
                        "method": "GET",
                        "header": [
                            {
                                "key": "Content-Type",
                                "value": "application\/json"
                            },
                            {
                                "key": "Accept",
                                "value": "application\/json"
                            }
                        ],
                        "body": null,
                        "description": "Gets a list of users",
                        "auth": {
                            "type": "noauth"
                        }
                    },
                    "response": [
                        {
                            "header": [],
                            "code": 200,
                            "body": "{\"data\":[{\"id\":40,\"name\":\"Jerod Eichmann\",\"email\":\"bahringer.petra@example.net\",\"created_at\":\"2024-01-26 05:28:23\",\"updated_at\":\"2024-01-26 05:28:23\"},{\"id\":41,\"name\":\"Leonel Quigley\",\"email\":\"ben.upton@example.com\",\"created_at\":\"2024-01-26 05:28:23\",\"updated_at\":\"2024-01-26 05:28:23\"}]}",
                            "name": ""
                        }
                    ]
                },
                {
                    "name": "Display the specified resource.",
                    "request": {
                        "url": {
                            "host": "{{baseUrl}}",
                            "path": "api\/v1\/users\/:id",
                            "query": [],
                            "raw": "{{baseUrl}}\/api\/v1\/users\/:id",
                            "variable": [
                                {
                                    "id": "id",
                                    "key": "id",
                                    "value": "12",
                                    "description": "user id"
                                }
                            ]
                        },
                        "method": "GET",
                        "header": [
                            {
                                "key": "Content-Type",
                                "value": "application\/json"
                            },
                            {
                                "key": "Accept",
                                "value": "application\/json"
                            }
                        ],
                        "body": null,
                        "description": "",
                        "auth": {
                            "type": "noauth"
                        }
                    },
                    "response": [
                        {
                            "header": [],
                            "code": 200,
                            "body": "{\"data\":{\"id\":42,\"name\":\"Maiya Terry Sr.\",\"email\":\"pdamore@example.org\",\"created_at\":\"2024-01-26 05:28:23\",\"updated_at\":\"2024-01-26 05:28:23\"}}",
                            "name": ""
                        }
                    ]
                },
                {
                    "name": "Store a newly created resource in storage.",
                    "request": {
                        "url": {
                            "host": "{{baseUrl}}",
                            "path": "api\/v1\/users",
                            "query": [],
                            "raw": "{{baseUrl}}\/api\/v1\/users"
                        },
                        "method": "POST",
                        "header": [
                            {
                                "key": "Content-Type",
                                "value": "application\/json"
                            },
                            {
                                "key": "Accept",
                                "value": "application\/json"
                            }
                        ],
                        "body": {
                            "mode": "raw",
                            "raw": "{\"name\":\"John Doe\",\"email\":\"john.doe@example.com\"}"
                        },
                        "description": "",
                        "auth": {
                            "type": "noauth"
                        }
                    },
                    "response": [
                        {
                            "header": [],
                            "code": 200,
                            "body": "{\"data\":{\"id\":43,\"name\":\"Kasandra Stamm IV\",\"email\":\"vella.senger@example.net\",\"created_at\":\"2024-01-26 05:28:23\",\"updated_at\":\"2024-01-26 05:28:23\"}}",
                            "name": ""
                        }
                    ]
                },
                {
                    "name": "Update the specified resource in storage.",
                    "request": {
                        "url": {
                            "host": "{{baseUrl}}",
                            "path": "api\/v1\/users\/:id",
                            "query": [],
                            "raw": "{{baseUrl}}\/api\/v1\/users\/:id",
                            "variable": [
                                {
                                    "id": "id",
                                    "key": "id",
                                    "value": "1",
                                    "description": "The ID of the user."
                                }
                            ]
                        },
                        "method": "PATCH",
                        "header": [
                            {
                                "key": "Content-Type",
                                "value": "application\/json"
                            },
                            {
                                "key": "Accept",
                                "value": "application\/json"
                            }
                        ],
                        "body": {
                            "mode": "raw",
                            "raw": "{\"name\":\"John Doe\",\"email\":\"john.doe@example.com\"}"
                        },
                        "description": "",
                        "auth": {
                            "type": "noauth"
                        }
                    },
                    "response": [
                        {
                            "header": [],
                            "code": 200,
                            "body": "{\"data\":{\"id\":44,\"name\":\"Hardy Nolan V\",\"email\":\"rswift@example.com\",\"created_at\":\"2024-01-26 05:28:23\",\"updated_at\":\"2024-01-26 05:28:23\"}}",
                            "name": ""
                        }
                    ]
                },
                {
                    "name": "Remove the specified resource from storage.",
                    "request": {
                        "url": {
                            "host": "{{baseUrl}}",
                            "path": "api\/v1\/users\/:id",
                            "query": [],
                            "raw": "{{baseUrl}}\/api\/v1\/users\/:id",
                            "variable": [
                                {
                                    "id": "id",
                                    "key": "id",
                                    "value": "10",
                                    "description": "user id"
                                }
                            ]
                        },
                        "method": "DELETE",
                        "header": [
                            {
                                "key": "Content-Type",
                                "value": "application\/json"
                            },
                            {
                                "key": "Accept",
                                "value": "application\/json"
                            }
                        ],
                        "body": null,
                        "description": "",
                        "auth": {
                            "type": "noauth"
                        }
                    },
                    "response": [
                        {
                            "header": [],
                            "code": 200,
                            "body": "{\"data\": \"success\"}",
                            "name": ""
                        }
                    ]
                }
            ]
        }
    ],
    "auth": {
        "type": "noauth"
    }
}